<?xml version="1.0" encoding="UTF-8" standalone="yes"?>
<ns1:courses xmlns:ns1="http://www.studer-raimann.ch/CourseImport">
  <ns1:course>
    <ns1:refId>66</ns1:refId>
    <ns1:title>Theo1</ns1:title>
    <ns1:description>Testkurs</ns1:description>
    <ns1:hierarchy>65</ns1:hierarchy>
    <ns1:courseAdmins>root</ns1:courseAdmins>
    <ns1:online>true</ns1:online>
    <ns1:directRegistration>true</ns1:directRegistration>
    <ns1:welcomeMail>true</ns1:welcomeMail>
    <ns1:courseTimeframe>
      <ns1:courseBeginningDate>2015-01-28</ns1:courseBeginningDate>
      <ns1:courseEndDate>2017-02-20</ns1:courseEndDate>
    </ns1:courseTimeframe>
    <ns1:courseInscriptionTimeframe/>
  </ns1:course>
  <ns1:course>
    <ns1:title>Gruppe1</ns1:title>
    <ns1:description>Gruppe1</ns1:description>
    <ns1:hierarchy>66</ns1:hierarchy>
    <ns1:courseAdmins>root</ns1:courseAdmins>
    <ns1:online>true</ns1:online>
    <ns1:directRegistration>true</ns1:directRegistration>
    <ns1:welcomeMail>false</ns1:welcomeMail>
    <ns1:courseTimeframe>
      <ns1:courseBeginningDate>2015-01-28</ns1:courseBeginningDate>
      <ns1:courseEndDate>2017-02-20</ns1:courseEndDate>
    </ns1:courseTimeframe>
    <ns1:courseInscriptionTimeframe>
      <ns1:courseInscriptionBeginningDate>2016-11-22</ns1:courseInscriptionBeginningDate>
      <ns1:courseInscriptionBeginningTime>13:00:00</ns1:courseInscriptionBeginningTime>
      <ns1:courseInscriptionEndDate>2016-11-29</ns1:courseInscriptionEndDate>
      <ns1:courseInscriptionEndTime>23:59:59</ns1:courseInscriptionEndTime>
    </ns1:courseInscriptionTimeframe>
  </ns1:course>
  <ns1:course>
    <ns1:title>Gruppe2</ns1:title>
    <ns1:description>Gruppe2</ns1:description>
    <ns1:hierarchy>66</ns1:hierarchy>
    <ns1:courseAdmins>root</ns1:courseAdmins>
    <ns1:online>true</ns1:online>
    <ns1:directRegistration>true</ns1:directRegistration>
    <ns1:welcomeMail>false</ns1:welcomeMail>
    <ns1:courseTimeframe>
      <ns1:courseBeginningDate>2015-01-28</ns1:courseBeginningDate>
      <ns1:courseEndDate>2017-02-20</ns1:courseEndDate>
    </ns1:courseTimeframe>
    <ns1:courseInscriptionTimeframe>
      <ns1:courseInscriptionBeginningDate>2016-11-22</ns1:courseInscriptionBeginningDate>
      <ns1:courseInscriptionBeginningTime>13:00:00</ns1:courseInscriptionBeginningTime>
      <ns1:courseInscriptionEndDate>2016-11-29</ns1:courseInscriptionEndDate>
      <ns1:courseInscriptionEndTime>23:59:59</ns1:courseInscriptionEndTime>
    </ns1:courseInscriptionTimeframe>
  </ns1:course>
  <ns1:course>
    <ns1:title>Gruppe3</ns1:title>
    <ns1:description>Gruppe3</ns1:description>
    <ns1:hierarchy>66</ns1:hierarchy>
    <ns1:courseAdmins>root</ns1:courseAdmins>
    <ns1:online>true</ns1:online>
    <ns1:directRegistration>true</ns1:directRegistration>
    <ns1:welcomeMail>false</ns1:welcomeMail>
    <ns1:courseTimeframe>
      <ns1:courseBeginningDate>2015-01-28</ns1:courseBeginningDate>
      <ns1:courseEndDate>2017-02-20</ns1:courseEndDate>
    </ns1:courseTimeframe>
    <ns1:courseInscriptionTimeframe>
      <ns1:courseInscriptionBeginningDate>2016-11-22</ns1:courseInscriptionBeginningDate>
      <ns1:courseInscriptionBeginningTime>13:00:00</ns1:courseInscriptionBeginningTime>
      <ns1:courseInscriptionEndDate>2016-11-29</ns1:courseInscriptionEndDate>
      <ns1:courseInscriptionEndTime>23:59:59</ns1:courseInscriptionEndTime>
    </ns1:courseInscriptionTimeframe>
  </ns1:course>
  <ns1:course>
    <ns1:title>Gruppe4</ns1:title>
    <ns1:description>Gruppe4</ns1:description>
    <ns1:hierarchy>66</ns1:hierarchy>
    <ns1:courseAdmins>root</ns1:courseAdmins>
    <ns1:online>true</ns1:online>
    <ns1:directRegistration>true</ns1:directRegistration>
    <ns1:welcomeMail>false</ns1:welcomeMail>
    <ns1:courseTimeframe>
      <ns1:courseBeginningDate>2015-01-28</ns1:courseBeginningDate>
      <ns1:courseEndDate>2017-02-20</ns1:courseEndDate>
    </ns1:courseTimeframe>
    <ns1:courseInscriptionTimeframe>
      <ns1:courseInscriptionBeginningDate>2016-11-22</ns1:courseInscriptionBeginningDate>
      <ns1:courseInscriptionBeginningTime>13:00:00</ns1:courseInscriptionBeginningTime>
      <ns1:courseInscriptionEndDate>2016-11-29</ns1:courseInscriptionEndDate>
      <ns1:courseInscriptionEndTime>23:59:59</ns1:courseInscriptionEndTime>
    </ns1:courseInscriptionTimeframe>
  </ns1:course>
  <ns1:course>
    <ns1:title>Gruppe5</ns1:title>
    <ns1:description>Gruppe5</ns1:description>
    <ns1:hierarchy>66</ns1:hierarchy>
    <ns1:courseAdmins>root</ns1:courseAdmins>
    <ns1:online>true</ns1:online>
    <ns1:directRegistration>true</ns1:directRegistration>
    <ns1:welcomeMail>false</ns1:welcomeMail>
    <ns1:courseTimeframe>
      <ns1:courseBeginningDate>2015-01-28</ns1:courseBeginningDate>
      <ns1:courseEndDate>2017-02-20</ns1:courseEndDate>
    </ns1:courseTimeframe>
    <ns1:courseInscriptionTimeframe>
      <ns1:courseInscriptionBeginningDate>2016-11-22</ns1:courseInscriptionBeginningDate>
      <ns1:courseInscriptionBeginningTime>13:00:00</ns1:courseInscriptionBeginningTime>
      <ns1:courseInscriptionEndDate>2016-11-29</ns1:courseInscriptionEndDate>
      <ns1:courseInscriptionEndTime>23:59:59</ns1:courseInscriptionEndTime>
    </ns1:courseInscriptionTimeframe>
  </ns1:course>
</ns1:courses>
